atlas_object/__init__.py
atlas_object/_version.py
atlas_object/atlas_class.py
atlas_object/lightcurve_class.py
atlas_object/rolling.py
atlas_object/sigma_clipping.py
atlas_object/utils.py
ATLAS_Object-0.1.0.dist-info/LICENSE
ATLAS_Object-0.1.0.dist-info/METADATA
ATLAS_Object-0.1.0.dist-info/WHEEL
ATLAS_Object-0.1.0.dist-info/top_level.txt
ATLAS_Object-0.1.0.dist-info/RECORD
