Metadata-Version: 2.1
Name: ATLAS-Object
Version: 0.1.0
Summary: For clening ATLAS light curves
Home-page: https://github.com/temuller/atlas_object
Author: Tomás Enrique Müller-Bravo
Author-email: t.e.muller-bravo@ice.csic.es
License: MIT
Classifier: Programming Language :: Python :: 3
Classifier: License :: OSI Approved :: MIT License
Classifier: Operating System :: OS Independent
Requires-Python: >=3.8
License-File: LICENSE
Requires-Dist: numpy
Requires-Dist: pandas
Requires-Dist: astropy
Requires-Dist: matplotlib
Requires-Dist: jupyterlab
